setup.py
reform/__init__.py
reform/_ordered_dict.py
reform/field.py
reform/form.py
reform/widget.py
reform.egg-info/PKG-INFO
reform.egg-info/SOURCES.txt
reform.egg-info/dependency_links.txt
reform.egg-info/requires.txt
reform.egg-info/top_level.txt