Metadata-Version: 1.0
Name: reform
Version: 0.1.0
Summary: Validate and convert forms
Home-page: UNKNOWN
Author: Henry Precheur
Author-email: henry@precheur.org
License: ISCL
Platform: UNKNOWN
Classifier: Environment :: Web Environment
Classifier: Operating System :: OS Independent
Classifier: Development Status :: 3 - Alpha
Classifier: Intended Audience :: Developers
Classifier: License :: OSI Approved :: ISC License (ISCL)
Classifier: Programming Language :: Python :: 2.6
